<?xml version="1.0" encoding="UTF-8"?>
<!DOCTYPE beans PUBLIC "-//SPRING//DTD BEAN//EN" "http://www.springframework.org/dtd/spring-beans.dtd">

<beans>
    <bean id="mylutece-openam.authentication" class="fr.paris.lutece.plugins.mylutece.modules.openam.authentication.OpenamAuthentication"/>

    <bean id="mylutece-openam.apiAuthenticate" class="fr.paris.lutece.plugins.mylutece.modules.openam.service.OpenamAPI">
        <property name="name">
            <value>authenticate</value>
        </property>
        <property name="url">
            <value>http://v69.rec.apps.paris.mdp/v69/json/authenticate</value>
        </property>
    </bean>
   
    <bean id="mylutece-openam.apiSession" class="fr.paris.lutece.plugins.mylutece.modules.openam.service.OpenamAPI">
        <property name="name">
            <value>session</value>
        </property>
        <property name="url">
            <value>http://v69.rec.apps.paris.mdp/v69/json/sessions/</value>
        </property>
      </bean>
    
    <bean id="mylutece-openam.apiUsers" class="fr.paris.lutece.plugins.mylutece.modules.openam.service.OpenamAPI">
        <property name="name">
            <value>users</value>
        </property>
        <property name="url">
            <value>http://v69.rec.apps.paris.mdp/v69/json/users/</value>
        </property>
    </bean>
   <bean id="mylutece-openam.openamLuteceUserSessionService" class="fr.paris.lutece.plugins.mylutece.modules.openam.service.OpenamLuteceUserSessionService"/>
  
  
</beans>
